{"cameraMode":{"drawMode":0,"name":"Shaded","section":"Shading Mode"},"sceneLighting":false,"audioPlay":false,"sceneViewState":{"showFog":true,"showMaterialUpdate":false,"showSkybox":false,"showFlares":true,"showImageEffects":true,"showParticleSystems":true},"in2DMode":false,"pivot":{"x":0.40430188179016116,"y":5.771810531616211,"z":0.2128915786743164},"rotation":{"x":0.2694636583328247,"y":0.20319794118404389,"z":-0.058275360614061359,"w":0.9395264983177185},"size":12.358525276184082,"orthographic":false}